loras/__init__.py
loras/loras.py
loras-0.0.22b0.dist-info/LICENSE
loras-0.0.22b0.dist-info/METADATA
loras-0.0.22b0.dist-info/WHEEL
loras-0.0.22b0.dist-info/top_level.txt
loras-0.0.22b0.dist-info/RECORD
