Metadata-Version: 2.1
Name: loras
Version: 0.0.22b0
Summary: A small package for LoRAS oversampling
Home-page: https://github.com/narek-davtyan/LoRAS
Author: Saptarshi Bej, Narek Davtyan
Author-email: davtyannarek@hotmail.com
License: UNKNOWN
Platform: UNKNOWN
Classifier: Programming Language :: Python :: 3
Classifier: License :: OSI Approved :: MIT License
Classifier: Operating System :: OS Independent
Requires-Dist: scikit-learn
Requires-Dist: numpy
